{
	"SN1997G":{
		"name":"SN1997G",
		"aliases":[
			"SN1997G"
		],
		"sources":[
			{
				"name":"Asiago Supernova Catalogue",
				"url":"http://graspa.oapd.inaf.it/cgi-bin/sncat.php",
				"alias":"1",
				"secondary":true
			},
			{
				"name":"Lennarz, Altmann, & Wiebusch (2012)",
				"url":"http://adsabs.harvard.edu/abs/2012A&A...538A.120L",
				"bibcode":"2012A&A...538A.120L",
				"alias":"2"
			},
			{
				"name":"IAUC 6540",
				"url":"http://www.cbat.eps.harvard.edu/iauc/06500/06540.html",
				"alias":"3"
			},
			{
				"name":"Latest Supernovae",
				"url":"http://www.rochesterastronomy.org/snimages/snredshiftall.html",
				"alias":"4",
				"secondary":true
			},
			{
				"name":"NED-D",
				"url":"http://ned.ipac.caltech.edu/Library/Distances/",
				"alias":"5",
				"secondary":true
			},
			{
				"name":"Lorenzi (2010)",
				"url":"http://adsabs.harvard.edu/abs/2010arXiv1006.2112L",
				"bibcode":"2010arXiv1006.2112L",
				"alias":"6"
			},
			{
				"name":"Amanullah et al. (2010)",
				"url":"http://adsabs.harvard.edu/abs/2010ApJ...716..712A",
				"bibcode":"2010ApJ...716..712A",
				"alias":"7"
			},
			{
				"name":"Kowalski et al. (2008)",
				"url":"http://adsabs.harvard.edu/abs/2008ApJ...686..749K",
				"bibcode":"2008ApJ...686..749K",
				"alias":"8"
			},
			{
				"name":"Hicken et al. (2009)",
				"url":"http://adsabs.harvard.edu/abs/2009ApJ...700.1097H",
				"bibcode":"2009ApJ...700.1097H",
				"alias":"9"
			}
		],
		"claimedtype":[
			{
				"value":"Ia",
				"source":"1,2,3,4"
			}
		],
		"comovingdist":[
			{
				"value":"2140",
				"source":"6,5",
				"unit":"Mpc"
			},
			{
				"value":"3230",
				"source":"7,5",
				"unit":"Mpc"
			},
			{
				"value":"4240",
				"source":"8,5",
				"unit":"Mpc"
			},
			{
				"value":"4810",
				"source":"9,5",
				"unit":"Mpc"
			}
		],
		"dec":[
			{
				"value":"-03:16:04.0",
				"source":"1,2,3,4",
				"unit":"nospace"
			}
		],
		"discover":[
			{
				"value":"1997/1/5",
				"source":"1"
			}
		],
		"discoverdate":[
			{
				"value":"1997/01/05",
				"source":"2,3,4"
			}
		],
		"discoverer":[
			{
				"value":"SCP",
				"source":"1"
			},
			{
				"value":"Supernova Cosmology Project",
				"source":"3,4"
			}
		],
		"galdec":[
			{
				"value":"-03:16:04",
				"source":"1",
				"unit":"nospace"
			},
			{
				"value":"-03:16:04.0",
				"source":"2"
			}
		],
		"galra":[
			{
				"value":"04:58:30",
				"source":"1",
				"unit":"nospace"
			},
			{
				"value":"04:58:30.00",
				"source":"2"
			}
		],
		"host":[
			{
				"value":"A045830-0316",
				"source":"1"
			}
		],
		"lumdist":[
			{
				"value":"4870",
				"source":"D",
				"kind":"host",
				"unit":"Mpc"
			}
		],
		"maxabsmag":[
			{
				"value":"-19.7",
				"source":"D"
			}
		],
		"maxappmag":[
			{
				"value":"23.7",
				"source":"D"
			}
		],
		"maxdate":[
			{
				"value":"1997/01/05",
				"source":"D"
			}
		],
		"ra":[
			{
				"value":"04:58:30.23",
				"source":"1,2,3,4",
				"unit":"nospace"
			}
		],
		"redshift":[
			{
				"value":"0.763",
				"source":"1",
				"kind":"host"
			}
		],
		"velocity":[
			{
				"value":"154000",
				"source":"D",
				"kind":"host",
				"unit":"km/s"
			}
		],
		"photometry":[
			{
				"timeunit":"MJD",
				"time":"50452.5",
				"magnitude":"23.7",
				"source":"3,4"
			},
			{
				"timeunit":"MJD",
				"time":"50453.0",
				"magnitude":"23.7",
				"source":"2"
			}
		]
	}
}