{
	"SN1992L":{
		"name":"SN1992L",
		"aliases":[
			"SN1992L"
		],
		"sources":[
			{
				"name":"Asiago Supernova Catalogue",
				"url":"http://graspa.oapd.inaf.it/cgi-bin/sncat.php",
				"alias":"1",
				"secondary":true
			},
			{
				"name":"Lennarz, Altmann, & Wiebusch (2012)",
				"url":"http://adsabs.harvard.edu/abs/2012A&A...538A.120L",
				"bibcode":"2012A&A...538A.120L",
				"alias":"2"
			},
			{
				"name":"IAUC 5469",
				"url":"http://www.cbat.eps.harvard.edu/iauc/05400/05469.html",
				"alias":"3"
			},
			{
				"name":"Latest Supernovae",
				"url":"http://www.rochesterastronomy.org/snimages/snredshiftall.html",
				"alias":"4",
				"secondary":true
			}
		],
		"dec":[
			{
				"value":"-47:16:51.0",
				"source":"1,2,3,4",
				"unit":"nospace"
			}
		],
		"discoverdate":[
			{
				"value":"1992/03/03",
				"source":"1,2,3,4"
			}
		],
		"discoverer":[
			{
				"value":"McNaught",
				"source":"1"
			},
			{
				"value":"Robert McNaught",
				"source":"3,4"
			}
		],
		"host":[
			{
				"value":"A073536-4716",
				"source":"1"
			},
			{
				"value":"2MASX J07353695-4716453",
				"source":"3,4"
			}
		],
		"hostdec":[
			{
				"value":"-47:16:51",
				"source":"1",
				"unit":"nospace"
			},
			{
				"value":"-47:16:51.0",
				"source":"2"
			}
		],
		"hostra":[
			{
				"value":"07:35:36",
				"source":"1",
				"unit":"nospace"
			},
			{
				"value":"07:35:36.00",
				"source":"2"
			}
		],
		"maxappmag":[
			{
				"value":"20",
				"source":"D,2"
			}
		],
		"maxband":[
			{
				"value":"R",
				"source":"D,2"
			}
		],
		"maxdate":[
			{
				"value":"1992/03/03",
				"source":"D,2"
			}
		],
		"ra":[
			{
				"value":"07:35:36.32",
				"source":"1,2,3,4",
				"unit":"nospace"
			}
		],
		"photometry":[
			{
				"timeunit":"MJD",
				"time":"48683.5",
				"magnitude":"20.0",
				"source":"3,4"
			},
			{
				"timeunit":"MJD",
				"time":"48684.0",
				"band":"R",
				"magnitude":"20.0",
				"source":"2"
			}
		]
	}
}